{
    "name": "Vanessa Davis",
    "age": 97,
    "address": {
        "street": "Eric Grove",
        "city": "North James",
        "state": "Utah",
        "zip": "54785"
    },
    "contact": {
        "phone": "001-771-886-9376x5985",
        "servicePhone": "800374648"
    },
    "birthday": "1928-31-10",
    "ip": "67.176.189.140",
    "foo": "bar",
    "profile": {
        "about": "Available leave read toward pass building while. Only past he bit perform. So else head stop help international.\nAnd account not push. Trial piece east day.",
        "bio": "Security especially then lawyer able relationship offer. Kind speech language leave."
    },
    "currency": [
        "KRW",
        "South Korean won"
    ]
}